tinyblog/admin.py
tinyblog/search_indexes.py
tinyblog/urls.py
tinyblog/models.py
tinyblog/feeds.py
tinyblog/forms.py
tinyblog/__init__.py
tinyblog/templatetags/tinyblog_tags.py
tinyblog/templatetags/__init__.py
tinyblog/views/subscription.py
tinyblog/views/json.py
tinyblog/views/__init__.py
tinyblog/utils/mail.py
tinyblog/utils/site.py
tinyblog/utils/tinybleach.py
tinyblog/utils/__init__.py
tinyblog/management/__init__.py
tinyblog/management/commands/mail_subscribers.py
tinyblog/management/commands/import_tinyblog.py
tinyblog/management/commands/__init__.py
tinyblog/templates/base.html
tinyblog/templates/tinyblog/_subscribe.html
tinyblog/templates/tinyblog/_post_date.html
tinyblog/templates/tinyblog/post_archive_year.html
tinyblog/templates/tinyblog/_post_body.html
tinyblog/templates/tinyblog/_subscribe_confirmed.html
tinyblog/templates/tinyblog/subscribe_thanks.html
tinyblog/templates/tinyblog/base.html
tinyblog/templates/tinyblog/subscribe_confirmed.html
tinyblog/templates/tinyblog/unsubscribe.html
tinyblog/templates/tinyblog/comments.html
tinyblog/templates/tinyblog/_post_preview.html
tinyblog/templates/tinyblog/_subscription_form.html
tinyblog/templates/tinyblog/post_archive.html
tinyblog/templates/tinyblog/_unsubscribe.html
tinyblog/templates/tinyblog/_unsubscribe_form.html
tinyblog/templates/tinyblog/_subscribe_thanks.html
tinyblog/templates/tinyblog/subscribe.html
tinyblog/templates/tinyblog/unsubscribe_form.html
tinyblog/templates/tinyblog/_post.html
tinyblog/templates/tinyblog/post_archive_month.html
tinyblog/templates/tinyblog/post.html
tinyblog/templates/tinyblog/emails/invite_subscription.subj
tinyblog/templates/tinyblog/emails/confirm_subscription.subj
tinyblog/templates/tinyblog/emails/invite_subscription.txt
tinyblog/templates/tinyblog/emails/confirm_subscription.html
tinyblog/templates/tinyblog/emails/blog_post.html
tinyblog/templates/tinyblog/emails/unsubscribe_link.txt
tinyblog-0.5.2.dist-info/DESCRIPTION.rst
tinyblog-0.5.2.dist-info/pydist.json
tinyblog-0.5.2.dist-info/top_level.txt
tinyblog-0.5.2.dist-info/RECORD
tinyblog-0.5.2.dist-info/WHEEL
tinyblog-0.5.2.dist-info/METADATA
