Metadata-Version: 2.0
Name: tinyblog
Version: 0.5.2
Summary: A Django app for a very simple blog.
Home-page: https://github.com/dominicrodger/tinyblog/
Author: Dominic Rodger
Author-email: UNKNOWN
License: BSD
Platform: UNKNOWN
Classifier: Framework :: Django
Classifier: Intended Audience :: Developers
Classifier: License :: OSI Approved :: BSD License
Classifier: Operating System :: OS Independent
Classifier: Topic :: Software Development
Classifier: Programming Language :: Python :: 2
Classifier: Programming Language :: Python :: 2.7
Requires-Dist: Django (>=1.4)
Requires-Dist: requests (==1.2.0)
Requires-Dist: django-tinymce (==1.5.3)
Requires-Dist: django-uuidfield (==0.4.0)
Requires-Dist: bleach (==1.2.2)
